{
  "453704409": {
    "title": "日本政府 4 月 9 日基本决定将福岛核污水排入大海，排污入海将带来哪些后果？",
    "url": "https://www.zhihu.com/question/453704409",
    "hot": "3057 万热度",
    "answerCount": 653
  },
  "454054826": {
    "title": "如何看待美国黑人军官被两名白人警察拦下殴打、喷辣椒水？",
    "url": "https://www.zhihu.com/question/454054826",
    "hot": "1771 万热度",
    "answerCount": 88
  },
  "453714590": {
    "title": "如何看待 CNN 记者摊牌就是要抹黑中国，「要让中国在国际舞台上看起来像个坏蛋」？为何西方媒体要抹黑中国？",
    "url": "https://www.zhihu.com/question/453714590",
    "hot": "1547 万热度",
    "answerCount": 394
  },
  "454007003": {
    "title": "如何看待肯德基误把消毒水给女子饮用，致其糜烂性胃炎和胃痉挛？相关人员应承担怎样的责任？",
    "url": "https://www.zhihu.com/question/454007003",
    "hot": "1464 万热度",
    "answerCount": 329
  },
  "454071132": {
    "title": "2021 LPL 春季胜者组决赛 FPX 3:2 击败 EDG 晋级总决赛，如何评价这场比赛？",
    "url": "https://www.zhihu.com/question/454071132",
    "hot": "1440 万热度",
    "answerCount": 304
  },
  "454016260": {
    "title": "如何看待元气森林回应「乳茶无糖标识错误」：改为「低糖」，购买过的消费者可领 20 元现金红包？",
    "url": "https://www.zhihu.com/question/454016260",
    "hot": "1361 万热度",
    "answerCount": 321
  },
  "453645866": {
    "title": "为何《进击的巨人》的 139 话在日本几乎是大受好评？",
    "url": "https://www.zhihu.com/question/453645866",
    "hot": "1050 万热度",
    "answerCount": 179
  },
  "454063985": {
    "title": "岳云鹏称 128G 手机可用内存仅 112G，系统内存应厂家消化，你认同吗？可用内存与宣传不符算虚假宣传吗？",
    "url": "https://www.zhihu.com/question/454063985",
    "hot": "1000 万热度",
    "answerCount": 324
  },
  "452942849": {
    "title": "安徽农业大学学生拒服兵役被罚 4 万余元，两年内不得复学，什么算拒服兵役？后果有多严重？",
    "url": "https://www.zhihu.com/question/452942849",
    "hot": "965 万热度",
    "answerCount": 230
  },
  "454031777": {
    "title": "如何看待游客在三亚吃海胆蒸蛋没海胆，官方称「当季本地海胆汁多肉少，未发现掉包」？如何从法律角度解读？",
    "url": "https://www.zhihu.com/question/454031777",
    "hot": "771 万热度",
    "answerCount": 254
  },
  "453333735": {
    "title": "如何评价天蚕土豆新书《万相之王》？",
    "url": "https://www.zhihu.com/question/453333735",
    "hot": "584 万热度",
    "answerCount": 126
  },
  "441692710": {
    "title": "未来 5 年，有没有取代房子的最好投资？",
    "url": "https://www.zhihu.com/question/441692710",
    "hot": "558 万热度",
    "answerCount": 443
  },
  "406439662": {
    "title": "听说江西人很能吃辣，是真的吗？",
    "url": "https://www.zhihu.com/question/406439662",
    "hot": "539 万热度",
    "answerCount": 297
  },
  "453680714": {
    "title": "如何看待男子花费 2 万余元植发后仍头秃，起诉后因无机构可鉴定毛囊存活率而败诉？他还能如何维权？",
    "url": "https://www.zhihu.com/question/453680714",
    "hot": "504 万热度",
    "answerCount": 100
  },
  "453979353": {
    "title": "为什么《进击的巨人》在结局借鉴了叛逆鲁鲁修的结局却不如鲁鲁修获得广大好评？",
    "url": "https://www.zhihu.com/question/453979353",
    "hot": "496 万热度",
    "answerCount": 45
  },
  "28352696": {
    "title": "猫临终前想要些什么?",
    "url": "https://www.zhihu.com/question/28352696",
    "hot": "492 万热度",
    "answerCount": 379
  },
  "454094663": {
    "title": "贤合庄火锅店天花板掉落，致夫妻俩一个手骨折一个脸被烫，火锅店应承担怎样的责任？",
    "url": "https://www.zhihu.com/question/454094663",
    "hot": "425 万热度",
    "answerCount": 36
  },
  "453684614": {
    "title": "顺丰控股暴雷标志着什么？",
    "url": "https://www.zhihu.com/question/453684614",
    "hot": "319 万热度",
    "answerCount": 61
  },
  "454001392": {
    "title": "如何评价许嵩新歌《昨夜书》？",
    "url": "https://www.zhihu.com/question/454001392",
    "hot": "319 万热度",
    "answerCount": 55
  },
  "453877246": {
    "title": "王小波逝世 24 周年之际，你有什么对小波说的吗？",
    "url": "https://www.zhihu.com/question/453877246",
    "hot": "305 万热度",
    "answerCount": 39
  },
  "453795080": {
    "title": "日本政府基本决定将福岛核污水排入大海，真的没办法阻止了吗？",
    "url": "https://www.zhihu.com/question/453795080",
    "hot": "299 万热度",
    "answerCount": 31
  },
  "22503810": {
    "title": "男生在大学真的需要女朋友么？",
    "url": "https://www.zhihu.com/question/22503810",
    "hot": "282 万热度",
    "answerCount": 382
  },
  "453992325": {
    "title": "《英雄联盟》聊天时为什么有人喜欢发 「1」？发的 「1」 都有哪些意思？",
    "url": "https://www.zhihu.com/question/453992325",
    "hot": "248 万热度",
    "answerCount": 66
  },
  "355087220": {
    "title": "对于久坐的人，屁股下加个坐垫有用吗？",
    "url": "https://www.zhihu.com/question/355087220",
    "hot": "245 万热度",
    "answerCount": 42
  },
  "423321345": {
    "title": "中国特有的狸花猫有多强大？",
    "url": "https://www.zhihu.com/question/423321345",
    "hot": "242 万热度",
    "answerCount": 481
  },
  "432404612": {
    "title": "我没玩过英雄联盟，平常只玩王者荣耀，能不能用一个通俗的解释说明 faker 的地位？",
    "url": "https://www.zhihu.com/question/432404612",
    "hot": "239 万热度",
    "answerCount": 690
  },
  "322856732": {
    "title": "你有没有在一瞬间突然认清了一个人？",
    "url": "https://www.zhihu.com/question/322856732",
    "hot": "203 万热度",
    "answerCount": 183
  },
  "454031031": {
    "title": "开会时，领导突然点名让你讲几句，但你却没有提前做好准备的时候，该怎么办？",
    "url": "https://www.zhihu.com/question/454031031",
    "hot": "200 万热度",
    "answerCount": 48
  },
  "375186677": {
    "title": "手机需要 12G 运行内存吗？",
    "url": "https://www.zhihu.com/question/375186677",
    "hot": "198 万热度",
    "answerCount": 104
  },
  "453811297": {
    "title": "还有一个星期要在学校 LoL 比赛上解说了，可我不经常玩 LoL，如何恶补 LoL 知识呢？",
    "url": "https://www.zhihu.com/question/453811297",
    "hot": "194 万热度",
    "answerCount": 43
  },
  "453944337": {
    "title": "如何评价景甜和张彬彬在《快乐大本营》中的表现？",
    "url": "https://www.zhihu.com/question/453944337",
    "hot": "189 万热度",
    "answerCount": 22
  },
  "342843416": {
    "title": "汉献帝为何不一剑杀了曹操，夺回大权？",
    "url": "https://www.zhihu.com/question/342843416",
    "hot": "181 万热度",
    "answerCount": 451
  },
  "446430795": {
    "title": "断舍离究竟有多爽？",
    "url": "https://www.zhihu.com/question/446430795",
    "hot": "166 万热度",
    "answerCount": 202
  },
  "453875656": {
    "title": "如何看待许多大学生宁愿听网课，也不愿意自己看书？",
    "url": "https://www.zhihu.com/question/453875656",
    "hot": "157 万热度",
    "answerCount": 225
  },
  "446146770": {
    "title": "你遇到过的最恐怖黑暗的事情是什么？",
    "url": "https://www.zhihu.com/question/446146770",
    "hot": "148 万热度",
    "answerCount": 44
  },
  "452126877": {
    "title": "五一想去南京玩，请问有什么建议吗?",
    "url": "https://www.zhihu.com/question/452126877",
    "hot": "136 万热度",
    "answerCount": 79
  },
  "453119283": {
    "title": "大爆炸起始于一个奇点，奇点势能被打破，导致能量不断转化为物质演变为宇宙。是什么导致了奇点平衡被打破？",
    "url": "https://www.zhihu.com/question/453119283",
    "hot": "132 万热度",
    "answerCount": 44
  },
  "439584381": {
    "title": "我花两千块买一个耳机，算智商税吗？",
    "url": "https://www.zhihu.com/question/439584381",
    "hot": "130 万热度",
    "answerCount": 224
  },
  "350710025": {
    "title": "短发可以软妹吗？",
    "url": "https://www.zhihu.com/question/350710025",
    "hot": "115 万热度",
    "answerCount": 710
  },
  "413029409": {
    "title": "你穿到一个虐文变成了一个试图勾引男主的恶毒女配，怎么办？",
    "url": "https://www.zhihu.com/question/413029409",
    "hot": "106 万热度",
    "answerCount": 133
  },
  "396974171": {
    "title": "什么样的女生（男生）一看就很难追？",
    "url": "https://www.zhihu.com/question/396974171",
    "hot": "104 万热度",
    "answerCount": 87
  },
  "448136663": {
    "title": "有大神研究过华为 P40 上的鸿蒙 OS 2.0 吗？事实它到底是个全新的自主操作系统还是个套壳安卓？",
    "url": "https://www.zhihu.com/question/448136663",
    "hot": "103 万热度",
    "answerCount": 429
  },
  "453780965": {
    "title": "如何评价综艺《恰好是少年》第一期？",
    "url": "https://www.zhihu.com/question/453780965",
    "hot": "92 万热度",
    "answerCount": 31
  },
  "452076744": {
    "title": "蜀汉和东吴谁对魏战绩更好？",
    "url": "https://www.zhihu.com/question/452076744",
    "hot": "88 万热度",
    "answerCount": 22
  },
  "444923264": {
    "title": "如何评价《创造营 2021》的林墨？",
    "url": "https://www.zhihu.com/question/444923264",
    "hot": "88 万热度",
    "answerCount": 396
  },
  "361111920": {
    "title": "一台主机上只能保持最多 65535 个 TCP 连接吗？",
    "url": "https://www.zhihu.com/question/361111920",
    "hot": "84 万热度",
    "answerCount": 35
  },
  "19889186": {
    "title": "如何回答「宝洁八大问」？",
    "url": "https://www.zhihu.com/question/19889186",
    "hot": "80 万热度",
    "answerCount": 67
  },
  "453105533": {
    "title": "你会喜欢一个男生很久吗？",
    "url": "https://www.zhihu.com/question/453105533",
    "hot": "74 万热度",
    "answerCount": 239
  },
  "21475064": {
    "title": "瘦人如何长胖和增肌？",
    "url": "https://www.zhihu.com/question/21475064",
    "hot": "72 万热度",
    "answerCount": 101
  },
  "22109444": {
    "title": "Windows 平台有哪些值得推荐的常用软件？",
    "url": "https://www.zhihu.com/question/22109444",
    "hot": "72 万热度",
    "answerCount": 58
  },
  "429392239": {
    "title": "结过婚的女生对未婚女生有什么忠告？",
    "url": "https://www.zhihu.com/question/429392239",
    "hot": "72 万热度",
    "answerCount": 1964
  },
  "389827161": {
    "title": "单从外形出发，谁在你们心中最适合演《长歌行》？",
    "url": "https://www.zhihu.com/question/389827161",
    "hot": "71 万热度",
    "answerCount": 26
  },
  "26685253": {
    "title": "你看过的电影里的最绝望的死法是什么？",
    "url": "https://www.zhihu.com/question/26685253",
    "hot": "68 万热度",
    "answerCount": 878
  },
  "446794813": {
    "title": "苹果公司知道我在使用黑苹果（Hackintosh）吗？",
    "url": "https://www.zhihu.com/question/446794813",
    "hot": "68 万热度",
    "answerCount": 57
  },
  "452985050": {
    "title": "新手小白，女生想入一个手串，有推荐的吗？",
    "url": "https://www.zhihu.com/question/452985050",
    "hot": "66 万热度",
    "answerCount": 77
  },
  "446865075": {
    "title": "怎么才能节约装修的成本？",
    "url": "https://www.zhihu.com/question/446865075",
    "hot": "64 万热度",
    "answerCount": 117
  },
  "46266923": {
    "title": "《奇葩说》有哪些超级经典的句子？",
    "url": "https://www.zhihu.com/question/46266923",
    "hot": "59 万热度",
    "answerCount": 800
  },
  "342779357": {
    "title": "自己找人装修和找装修公司哪个好？",
    "url": "https://www.zhihu.com/question/342779357",
    "hot": "59 万热度",
    "answerCount": 102
  },
  "452184164": {
    "title": "Java 面试都只是背答案吗？",
    "url": "https://www.zhihu.com/question/452184164",
    "hot": "59 万热度",
    "answerCount": 24
  },
  "444986537": {
    "title": "「足坛」有哪些公认的水货，后来莫名其妙竟然踢出来了的球员？",
    "url": "https://www.zhihu.com/question/444986537",
    "hot": "59 万热度",
    "answerCount": 21
  },
  "348287427": {
    "title": "爸爸去世继承的房产，现在要出售，房屋中介说百分之二十的遗产税，是这样吗？100 万房子 20 万的税？",
    "url": "https://www.zhihu.com/question/348287427",
    "hot": "58 万热度",
    "answerCount": 245
  },
  "342482043": {
    "title": "你买过什么很贵但又很值的东西？",
    "url": "https://www.zhihu.com/question/342482043",
    "hot": "52 万热度",
    "answerCount": 2531
  },
  "439314149": {
    "title": "姚安娜毕业于哈佛大学计算机科学和统计学专业，为什么还要进娱乐圈？高学历人才进娱乐圈是趋势吗？",
    "url": "https://www.zhihu.com/question/439314149",
    "hot": "52 万热度",
    "answerCount": 2089
  },
  "62354587": {
    "title": "有什么比较耐吃的零食？",
    "url": "https://www.zhihu.com/question/62354587",
    "hot": "47 万热度",
    "answerCount": 1158
  },
  "30196004": {
    "title": "为什么喜欢心理学、哲学的人往往在境界上显得很深邃，在生活当中显得很幼稚？",
    "url": "https://www.zhihu.com/question/30196004",
    "hot": "46 万热度",
    "answerCount": 3262
  },
  "418006057": {
    "title": "为什么当我很爱一个人的时候会觉得很痛苦？",
    "url": "https://www.zhihu.com/question/418006057",
    "hot": "42 万热度",
    "answerCount": 68
  },
  "399883021": {
    "title": "先用隔离还是先用防晒？",
    "url": "https://www.zhihu.com/question/399883021",
    "hot": "42 万热度",
    "answerCount": 592
  },
  "453533419": {
    "title": "成都一大学生网购被骗后寻「反诈专线」再被骗 1.2 万，大学生如何识别网络诈骗？若被骗应该如何维权？",
    "url": "https://www.zhihu.com/question/453533419",
    "hot": "28 万热度",
    "answerCount": 83
  },
  "452554884": {
    "title": "有没有参加过保研夏令营的前辈，这样的个人陈述怎么样啊？",
    "url": "https://www.zhihu.com/question/452554884",
    "hot": "27 万热度",
    "answerCount": 23
  },
  "442551957": {
    "title": "表达能力不好，一说话脑子空白，是因为词汇量少还是不够自信？",
    "url": "https://www.zhihu.com/question/442551957",
    "hot": "27 万热度",
    "answerCount": 44
  },
  "448051943": {
    "title": "有哪些关于少年的文案？",
    "url": "https://www.zhihu.com/question/448051943",
    "hot": "26 万热度",
    "answerCount": 102
  },
  "453575313": {
    "title": "「有问题」的人，生活中有何不一样？",
    "url": "https://www.zhihu.com/question/453575313",
    "hot": "26 万热度",
    "answerCount": 45
  },
  "452561786": {
    "title": "考研英语在 4 月份除了记单词还应该怎么复习？",
    "url": "https://www.zhihu.com/question/452561786",
    "hot": "25 万热度",
    "answerCount": 29
  }
}